pcheck/__init__.py
pcheck/__main__.py
pcheck/pcheck.py
pcheck-0.1.5.dist-info/LICENSE
pcheck-0.1.5.dist-info/METADATA
pcheck-0.1.5.dist-info/WHEEL
pcheck-0.1.5.dist-info/entry_points.txt
pcheck-0.1.5.dist-info/top_level.txt
pcheck-0.1.5.dist-info/RECORD
