Metadata-Version: 2.1
Name: pcheck
Version: 0.1.5
Summary: A easy to use and blazingly fast proxy checker written in python 
Home-page: https://github.com/ProtDos/pcheck
Author: CodingLive
Author-email: rootcode@duck.com
Classifier: Programming Language :: Python :: 3
Classifier: License :: OSI Approved :: MIT License
Classifier: Operating System :: OS Independent
Requires-Python: >=3.6
License-File: LICENSE
Requires-Dist: aiohttp
